visualization/__init__.py
visualization/version.py
visualization/visualizer2d.py
visualization/visualizer3d.py
visualization-1.0.0.dist-info/LICENSE
visualization-1.0.0.dist-info/METADATA
visualization-1.0.0.dist-info/WHEEL
visualization-1.0.0.dist-info/top_level.txt
visualization-1.0.0.dist-info/RECORD
